lazy_consul.py
setup.py
lazy_consul.egg-info/PKG-INFO
lazy_consul.egg-info/SOURCES.txt
lazy_consul.egg-info/dependency_links.txt
lazy_consul.egg-info/requires.txt
lazy_consul.egg-info/top_level.txt