Metadata-Version: 1.1
Name: lazy-consul
Version: 0.5
Summary: Lazy client library for the Consul Key/Value store
Home-page: https://github.com/Fatal1ty/lazy-consul
Author: Alexander Tikhonov
Author-email: UNKNOWN
License: MIT
Platform: all
Classifier: Intended Audience :: Developers
Classifier: License :: OSI Approved :: MIT License
Classifier: Programming Language :: Python
Classifier: Operating System :: OS Independent
Classifier: Topic :: Software Development :: Libraries :: Python Modules
Classifier: Topic :: System :: Clustering
